<IssueSpecification version="4">
  <Name>
    <en>Demo Voting Card</en>
    <nl>Demo Stempas</nl>
  </Name>
  <ShortName>
    <en>Demo Voting Card</en>
    <nl>Demo Stempas</nl>
  </ShortName>
  <SchemeManager>irma-demo</SchemeManager>
  <IssuerID>stemmen</IssuerID>
  <CredentialID>stempas</CredentialID>
  <Description>
    <en>Your voting card</en>
    <nl>Uw stempas</nl>
  </Description>
  <IssueURL>
    <en></en>
    <nl></nl>
  </IssueURL>
  <ShouldBeSingleton>true</ShouldBeSingleton>

  <Attributes>
    <Attribute id="election">
      <Name>
        <en>Election</en>
        <nl>Verkiezing</nl>
      </Name>
      <Description>
        <en>Election</en>
        <nl>Verkiezing</nl>
      </Description>
    </Attribute>
    <Attribute id="votingnumber" randomblind="true">
      <Name>
        <en>Voting number</en>
        <nl>Stemnummer</nl>
      </Name>
      <Description>
        <en>Voting number</en>
        <nl>Stemnummer</nl>
      </Description>
    </Attribute>
    <Attribute id="voteURL">
      <Name>
        <en>Vote URL</en>
        <nl>Stem URL</nl>
      </Name>
      <Description>
        <en>The URL on which votes can be registered</en>
        <nl>De URL waarop u uw stem uit kan brengen</nl>
      </Description>
    </Attribute>
    <Attribute id="start">
      <Name>
        <en>Start date</en>
        <nl>Startdatum</nl>
      </Name>
      <Description>
        <en>The date after which votes can be registered</en>
        <nl>De datum vanaf wanneer u uw stem uit kan brengen</nl>
      </Description>
    </Attribute>
    <Attribute id="end">
      <Name>
        <en>End date</en>
        <nl>Einddatum</nl>
      </Name>
      <Description>
        <en>The date after which votes can no longer be registered</en>
        <nl>De datum vanaf wanneer u uw stem niet meer uit kan brengen</nl>
      </Description>
    </Attribute>
  </Attributes>
</IssueSpecification>
